{
    "name": "Taktische Größe",
    "type": "submenu",
    "values": [
        {
            "name": "Verband",
            "type": "radio",
            "key": "formation"
        },
        {
            "name": "Zug",
            "type": "radio",
            "key": "platoon"
        },
        {
            "name": "Zugtrupp",
            "type": "radio",
            "key": "platoontroop"
        },
        {
            "name": "Gruppe",
            "type": "radio",
            "key": "group"
        },
        {
            "name": "Staffel",
            "type": "radio",
            "key": "echelon"
        },
        {
            "name": "Trupp",
            "type": "radio",
            "key": "troop"
        }
    ]
}